sanic_prometheus/__init__.py
sanic_prometheus/endpoint.py
sanic_prometheus/exceptions.py
sanic_prometheus/metrics.py
sanic_prometheus_mon-0.3.9.dist-info/LICENSE
sanic_prometheus_mon-0.3.9.dist-info/METADATA
sanic_prometheus_mon-0.3.9.dist-info/WHEEL
sanic_prometheus_mon-0.3.9.dist-info/top_level.txt
sanic_prometheus_mon-0.3.9.dist-info/RECORD
