Metadata-Version: 2.1
Name: sanic-prometheus-mon
Version: 0.3.9
Summary: Exposes Prometheus monitoring metrics of Sanic apps.
Home-page: https://github.com/valerylisay/sanic-prometheus-mon
Author: Dan Kruchinin
Author-email: dan.kruchinin@gmail.com
Maintainer: Valeriy Lisay
Maintainer-email: valery@lisay.ru
License: MIT
Keywords: python sanic prometheus monitoring metrics
Platform: any
Classifier: Intended Audience :: Developers
Classifier: Development Status :: 3 - Alpha
Classifier: License :: OSI Approved :: MIT License
Classifier: Operating System :: OS Independent
Classifier: Environment :: Web Environment
Classifier: Topic :: System :: Monitoring
Classifier: Topic :: Internet :: WWW/HTTP :: Dynamic Content
Classifier: Topic :: Software Development :: Libraries :: Python Modules
Classifier: Programming Language :: Python :: 3.6
Classifier: Programming Language :: Python :: 3.7
License-File: LICENSE
Requires-Dist: sanic (>=18.12)
Requires-Dist: prometheus-client (~=0.11.0)
Requires-Dist: psutil (~=5.8.0)
